[{"word":"facsimile","wordPron":"[f1k\u0027simili]","wordMean":"n.复制本,摹本"},{"word":"illuminating","wordPron":"[i\u0027lu:mineiti6]","wordMean":"adj.启示性的,启发的"},{"word":"tractability","wordPron":"[`tr1kt4\u0027biliti]","wordMean":"n.温顺"},{"word":"sensational","wordPron":"[sen\u0027sei54n4l]","wordMean":"adj.耸人听闻的,轰动的"},{"word":"domicile","wordPron":"[\u0027d3misail]","wordMean":"n.住处,住所"},{"word":"enliven","wordPron":"[in\u0027laiv4n]","wordMean":"v.使...更活跃"},{"word":"sapient","wordPron":"[\u0027seipi4nt]","wordMean":"adj.有智慧的"},{"word":"irritate","wordPron":"[\u0027iriteit]","wordMean":"v.激怒；刺激"},{"word":"rile","wordPron":"[rail]","wordMean":"v.使...恼火;激怒"},{"word":"alchemy","wordPron":"[\u00271lk4mi]","wordMean":"n.炼金术"},{"word":"cursive","wordPron":"[\u0027k4:siv]","wordMean":"adj.草书的"},{"word":"hypocrite","wordPron":"[\u0027hip4krit]","wordMean":"n.伪善者,伪君子"},{"word":"gorgeous","wordPron":"[\u0027g3:d94s]","wordMean":"adj.美丽的,极好的"},{"word":"revealing","wordPron":"[ri\u0027vili6]","wordMean":"adj.暴露的,裸露的;揭露性的"},{"word":"orient","wordPron":"[\u00273:ri4nt]","wordMean":"adj.上升的;v.确定方向；使熟悉情况"},{"word":"stilted","wordPron":"[\u0027stiltid]","wordMean":"adj.(文章,谈话)不自然的;夸张的"},{"word":"opulent","wordPron":"[\u00273pjul4nt]","wordMean":"adj.富裕的；充足的"},{"word":"exorbitant","wordPron":"[ig\u0027z3:bit4nt]","wordMean":"adj.过分的,过度的"},{"word":"systematic","wordPron":"[`sisti\u0027m1tik]","wordMean":"adj.有系统的,有条理的"},{"word":"putrefy","wordPron":"[\u0027pju:trifai]","wordMean":"v.使腐烂"},{"word":"heartrending","wordPron":"[\u0027ha:trendi6]","wordMean":"adj.令人心碎的"},{"word":"impinge","wordPron":"[im\u0027pind9]","wordMean":"v.侵犯;撞击"},{"word":"viral","wordPron":"[\u0027vai4r(4)l]","wordMean":"adj.病毒性的"},{"word":"formality","wordPron":"[f3:\u0027m1liti]","wordMean":"n.遵循的规范;正式"},{"word":"actuarial","wordPron":"[`1ktju\u0027e4ri4]","wordMean":"adj.(保险)精算的;保险计算的"},{"word":"principal","wordPron":"[\u0027prins4p4l]","wordMean":"adj.主要的,重要的"},{"word":"anaerobic","wordPron":"[1n`e4\u0027r4ubik]","wordMean":"adj.厌氧的n.厌氧微生物"},{"word":"delusion","wordPron":"[di\u0027lu:94n]","wordMean":"n.欺骗,幻想"},{"word":"vague","wordPron":"[veig]","wordMean":"adj.模糊的"},{"word":"abscond","wordPron":"[4b\u0027sk3nd]","wordMean":"v.潜逃,逃亡"},{"word":"imprecation","wordPron":"[impri\u0027kei54n]","wordMean":"n.咒语,诅咒"},{"word":"validate","wordPron":"[\u0027v1lideit]","wordMean":"v.使...生效"},{"word":"regal","wordPron":"[\u0027ri:g4l]","wordMean":"adj.帝王的；华丽的"},{"word":"unbridled","wordPron":"[8n\u0027braidld]","wordMean":"adj.放纵的"},{"word":"pier","wordPron":"[pi4]","wordMean":"n.桥墩；码头"},{"word":"formative","wordPron":"[\u0027f3:m4tiv]","wordMean":"adj.形成的,影响发展的"},{"word":"feigned","wordPron":"[\u0027feind]","wordMean":"adj.假装的；不真诚的"},{"word":"exemption","wordPron":"[ig\u0027zemp54n]","wordMean":"n.免除"},{"word":"transpose","wordPron":"[tr1n\u0027sp4uz]","wordMean":"v.变换位置,调换"},{"word":"enumerate","wordPron":"[i\u0027nju:m4reit]","wordMean":"v.列举,枚举"},{"word":"diagram","wordPron":"[\u0027dai4gr1m]","wordMean":"n.图解,图表"},{"word":"distress","wordPron":"[dis\u0027tres]","wordMean":"n.痛苦,悲痛"},{"word":"satire","wordPron":"[\u0027s1tai4]","wordMean":"n.讽刺(作品)"},{"word":"boom","wordPron":"[bu:m]","wordMean":"n.繁荣昌盛时期;v.发出深沉有回响的声音"},{"word":"resistant","wordPron":"[ri\u0027zist4nt]","wordMean":"adj.有抵抗力的,抵抗的"},{"word":"viscosity","wordPron":"[vis\u0027k3siti]","wordMean":"n.粘度,粘性"},{"word":"vitiate","wordPron":"[\u0027vi5ieit]","wordMean":"v.削弱,损害"},{"word":"sidesplitting","wordPron":"[\u0027said` spliti6]","wordMean":"adj.令人捧腹大笑的"},{"word":"daub","wordPron":"[d3:b]","wordMean":"v.涂抹；乱画"},{"word":"lugubrious","wordPron":"[lu:\u0027gu: bri4s]","wordMean":"adj.郁郁不乐的,悲哀的"},{"word":"crude","wordPron":"[kru:d]","wordMean":"adj.未提炼的；粗鲁的；n.原油"},{"word":"breadth","wordPron":"[bred7]","wordMean":"n.宽度"},{"word":"saber","wordPron":"[\u0027seib4(r)]","wordMean":"n.军刀,击剑用刀"},{"word":"unbecoming","wordPron":"[`8nbi\u0027k8mi6]","wordMean":"adj.不合身的;不得体的"},{"word":"havoc","wordPron":"[\u0027h1v4k]","wordMean":"n.大破坏,混乱"},{"word":"crockery","wordPron":"[\u0027kr3k4ri]","wordMean":"n.陶器,瓦器"},{"word":"dowdy","wordPron":"[\u0027d2udi]","wordMean":"adj.不整洁的,过旧的"},{"word":"fissure","wordPron":"[\u0027fi54]","wordMean":"n.裂缝,裂隙"},{"word":"deprecate","wordPron":"[\u0027deprikeit]","wordMean":"v.反对,轻视"},{"word":"misleading","wordPron":"[`mis\u0027li:di6]","wordMean":"adj.令人误解的"},{"word":"inedible","wordPron":"[in\u0027edib4l]","wordMean":"adj.不宜食用的"},{"word":"momentum","wordPron":"[m4u\u0027ment4m]","wordMean":"n.推进力,势头"},{"word":"hodgepodge","wordPron":"[\u0027h3d9p3d9]","wordMean":"n.混淆,杂菜"},{"word":"unprecedented","wordPron":"[8n\u0027presidentid]","wordMean":"adj.前所未有的"},{"word":"coy","wordPron":"[k3i]","wordMean":"adj.腼腆的,忸怩的"},{"word":"fossilize","wordPron":"[\u0027f3silaiz]","wordMean":"v.使...成为化石;使...过时"},{"word":"ensue","wordPron":"[in\u0027sju:]","wordMean":"v.继而发生"},{"word":"neophyte","wordPron":"[\u0027ni4ufait]","wordMean":"n.初学者,新手"},{"word":"clapper","wordPron":"[\u0027kl1p4]","wordMean":"n.铃舌；(复)拍板,响板"},{"word":"appetizer","wordPron":"[\u00271pitaiz4]","wordMean":"n.开胃品"},{"word":"lunatic","wordPron":"[\u0027lu:n4tik]","wordMean":"n.疯子；adj.极蠢的"},{"word":"lethal","wordPron":"[\u0027li:74l]","wordMean":"adj.致命的"},{"word":"qualified","wordPron":"[\u0027kw3lifaid]","wordMean":"adj.有资格的;有限制的"},{"word":"elm","wordPron":"[elm]","wordMean":"n.榆树"},{"word":"disengage","wordPron":"[\u0027disin\u0027geid9]","wordMean":"v.脱离,解开"},{"word":"fosse","wordPron":"[f3s]","wordMean":"n.护城河"},{"word":"entrench","wordPron":"[in\u0027trent5]","wordMean":"v.挖壕沟；确立"},{"word":"staccato","wordPron":"[st4\u0027k2:t4u]","wordMean":"adj.(音乐)断音的,不连贯的"},{"word":"liquefy","wordPron":"[\u0027likwifai]","wordMean":"v.液化,溶解"},{"word":"vanity","wordPron":"[\u0027v1niti]","wordMean":"n.虚荣,自负"},{"word":"cringe","wordPron":"[krind9]","wordMean":"v.畏缩；谄媚"},{"word":"ostentation","wordPron":"[`3sten\u0027tei54n]","wordMean":"n.夸示,炫耀"},{"word":"logistics","wordPron":"[l4\u0027d9istiks]","wordMean":"n.后勤学"},{"word":"sneer","wordPron":"[sni4]","wordMean":"v.嘲笑,鄙视"},{"word":"suspicious","wordPron":"[s4\u0027spi54s]","wordMean":"adj.怀疑的"},{"word":"reverend","wordPron":"[\u0027rev4r4nd]","wordMean":"adj.值得敬重的"},{"word":"engaging","wordPron":"[in\u0027geid9i6]","wordMean":"adj.迷人的,美丽动人的"},{"word":"despoil","wordPron":"[di\u0027sp3il]","wordMean":"v.夺取,抢夺"},{"word":"oratorio","wordPron":"[`3r4\u0027t3:ri4u]","wordMean":"n.清唱剧(没有舞台行动、 道具的戏剧)"},{"word":"cub","wordPron":"[k8b]","wordMean":"n.幼兽；年轻无经验的人"},{"word":"eulogy","wordPron":"[\u0027ju:l4d9i]","wordMean":"n.颂词,颂文"},{"word":"combustible","wordPron":"[k4m\u0027b8st4bl]","wordMean":"adj.易燃的；易激动的"},{"word":"securities","wordPron":"[si\u0027kju4ritiz]","wordMean":"n.证券"},{"word":"primeval","wordPron":"[prai\u0027mi:v4l]","wordMean":"adj.原始的,早期的"},{"word":"pliers","wordPron":"[\u0027plai4z]","wordMean":"n.钳子"},{"word":"cadaverous","wordPron":"[k4\u0027d1v4r4s]","wordMean":"adj.像尸体的,苍白的"},{"word":"harmony","wordPron":"[\u0027h2:m4ni]","wordMean":"n.相符,一致;协调,匀称"},{"word":"intangibility","wordPron":"[`int1nd94\u0027bil4ti]","wordMean":"n.无形,不可接触"},{"word":"caprice","wordPron":"[k4\u0027pri:s]","wordMean":"n.突如其来的念头,任性"},{"word":"incriminate","wordPron":"[in\u0027krimineit]","wordMean":"v.连累,牵连"},{"word":"omnivorous","wordPron":"[3m\u0027niv4r4s]","wordMean":"adj.杂食的；兴趣杂的"},{"word":"whelm","wordPron":"[welm]","wordMean":"v.用...覆盖,淹没"},{"word":"anthropoid","wordPron":"[\u00271n7r4p3id]","wordMean":"adj.像人类的;n.类人猿"},{"word":"reaffirm","wordPron":"[ri:4\u0027f4:m]","wordMean":"v.重新肯定"},{"word":"heir","wordPron":"[e4]","wordMean":"n.继承人"},{"word":"paradox","wordPron":"[\u0027p1r4d3ks]","wordMean":"n.矛盾,似矛盾而正确的说法"},{"word":"latitude","wordPron":"[\u0027l1titju:d]","wordMean":"n.言行自由"},{"word":"episodic","wordPron":"[`epi\u0027s3dik]","wordMean":"adj.偶然发生的,分散性的"},{"word":"archer","wordPron":"[\u00272:t54]","wordMean":"n.(运动或战争中的)弓箭手,射手"},{"word":"alcove","wordPron":"[\u00271lk4uv]","wordMean":"n.凹室"},{"word":"successively","wordPron":"[s4k\u0027sesivli]","wordMean":"adv.接连地,继续地"},{"word":"flask","wordPron":"[fl2:sk]","wordMean":"n.烧瓶,细颈瓶"},{"word":"cession","wordPron":"[\u0027se54n]","wordMean":"n.割让,转让"},{"word":"log","wordPron":"[l3g]","wordMean":"n./v.日志,记录;木头"},{"word":"squat","wordPron":"[skw3t]","wordMean":"v.蹲下;adj.矮胖的"},{"word":"hearken","wordPron":"[\u0027ha:k4n]","wordMean":"v.倾听"},{"word":"mast","wordPron":"[m2:st,m1st]","wordMean":"n.船桅,旗杆"},{"word":"invidious","wordPron":"[in\u0027vidi4s]","wordMean":"adj.惹人反感的,招人嫉妒的"},{"word":"tombstone","wordPron":"[\u0027tu:mst4un]","wordMean":"n.墓碑,墓石"},{"word":"materialize","wordPron":"[m4\u0027ti4ri4laiz]","wordMean":"v.赋予形体；实现"},{"word":"landmark","wordPron":"[\u0027l1ndm2:k]","wordMean":"n.陆标;里程碑"},{"word":"excel","wordPron":"[ik\u0027sel]","wordMean":"v.善于,擅长于"},{"word":"peevish","wordPron":"[\u0027pi:vi5]","wordMean":"adj.坏脾气的,易怒的"},{"word":"install","wordPron":"[in\u0027st3:l]","wordMean":"v.安装,装置;使就职"},{"word":"flip","wordPron":"[flip]","wordMean":"v.用指轻弹,蹦跳;adj.无礼的"},{"word":"hypochondria","wordPron":"[`haip4\u0027k3ndri4]","wordMean":"n.忧郁症,臆想病"},{"word":"intimate","wordPron":"[\u0027intimit]","wordMean":"v.暗示"},{"word":"barefaced","wordPron":"[be4\u0027feist]","wordMean":"adj.厚颜无耻的,公然的"},{"word":"wheedle","wordPron":"[\u0027wi:dl]","wordMean":"v.(用花言巧语)哄骗"},{"word":"baseboard","wordPron":"[\u0027beisb3:d]","wordMean":"n.脚板,护壁板"},{"word":"egregious","wordPron":"[i\u0027gri:d94s]","wordMean":"adj.(缺点等)过分的,惊人的"},{"word":"migrant","wordPron":"[\u0027maigr4nt]","wordMean":"n.移民,候鸟"},{"word":"hut","wordPron":"[h8t]","wordMean":"n.简陋的房子,棚"},{"word":"horizontal","wordPron":"[`h3ri\u0027z3ntl]","wordMean":"adj.水平的"},{"word":"stinginess","wordPron":"[\u0027sti6inis]","wordMean":"n.小气"},{"word":"strengthen","wordPron":"[\u0027stre674n,\u0027stren74n]","wordMean":"v.加强,使坚强"},{"word":"plaza","wordPron":"[\u0027pl2:z4]","wordMean":"n.广场；集市"},{"word":"warranted","wordPron":"[\u0027w3r4ntid]","wordMean":"adj.保证的;凭正当理由的"},{"word":"parasite","wordPron":"[\u0027p1r4sait]","wordMean":"n.寄生虫,食客"},{"word":"forge","wordPron":"[f3:d9]","wordMean":"n.铁匠铺；v.锤炼； 伪造"},{"word":"sodden","wordPron":"[\u0027s3dn]","wordMean":"adj.浸透了的"},{"word":"arthritis","wordPron":"[2:\u00277raitis]","wordMean":"n.关节炎"},{"word":"drizzle","wordPron":"[\u0027drizl]","wordMean":"v./n.下毛毛雨；毛毛雨"},{"word":"shade","wordPron":"[5eid]","wordMean":"n.阴影；细微差别"},{"word":"arena","wordPron":"[4\u0027ri:n4]","wordMean":"n.(角斗的)竞技场"},{"word":"articulate","wordPron":"[2:\u0027tikjuleit]","wordMean":"v.清楚说话；接合"},{"word":"tenant","wordPron":"[\u0027ten4nt]","wordMean":"n.房客"},{"word":"typhoon","wordPron":"[tai\u0027fu:n]","wordMean":"n.台风"},{"word":"sky-rocket","wordPron":"[\u0027skai`r3kit]","wordMean":"v.陡升,猛涨"},{"word":"overwhelming","wordPron":"[`4uv4\u0027welmi6]","wordMean":"adj.压倒性的,无法抵抗的"},{"word":"misconstrue","wordPron":"[`misk4n\u0027stru:]","wordMean":"v.误解,曲解"},{"word":"grill","wordPron":"[gril]","wordMean":"v.烤；拷问；n.烤架"},{"word":"adroit","wordPron":"[4\u0027dr3it]","wordMean":"adj.熟练的,灵巧的"},{"word":"figment","wordPron":"[\u0027figm4nt]","wordMean":"n.虚构的东西"},{"word":"stink","wordPron":"[sti6k]","wordMean":"v.发臭;n.臭味"},{"word":"reputable","wordPron":"[\u0027repjut4b4l]","wordMean":"adj.名誉好的"},{"word":"rescind","wordPron":"[ri\u0027sind]","wordMean":"v.废除,取消"},{"word":"abominate","wordPron":"[4\u0027b3mineit]","wordMean":"v.痛恨；厌恶"},{"word":"medley","wordPron":"[\u0027medli]","wordMean":"n.混合歌曲;混杂"},{"word":"exclaim","wordPron":"[ik\u0027skleim]","wordMean":"v.惊叫,呼喊"},{"word":"complaisant","wordPron":"[k4m\u0027pleiz4nt]","wordMean":"adj.顺从的,讨好的"},{"word":"vie","wordPron":"[vai]","wordMean":"v.竞争"},{"word":"cygnet","wordPron":"[\u0027signit]","wordMean":"n.幼天鹅"},{"word":"lynch","wordPron":"[lint5]","wordMean":"v.私刑处死"},{"word":"palpitate","wordPron":"[\u0027p1lpiteit]","wordMean":"v.(心脏)急速而不规则地跳动"},{"word":"holster","wordPron":"[\u0027h4ulst4]","wordMean":"n.手枪皮套"},{"word":"ethereal","wordPron":"[i\u00277i4ri4l]","wordMean":"adj.太空的；轻巧的"},{"word":"confuse","wordPron":"[k4n\u0027fju:z]","wordMean":"v.使迷惑;打乱"},{"word":"crepuscular","wordPron":"[kri\u0027p8skjul4]","wordMean":"adj.朦胧的,微明的"},{"word":"parse","wordPron":"[p2:z]","wordMean":"v.对...作语法分析"},{"word":"oddments","wordPron":"[\u00273dments]","wordMean":"n.残余物,零头"},{"word":"neologism","wordPron":"[ni:\u00273l4d9iz4m]","wordMean":"n.新字,新义"},{"word":"languish","wordPron":"[\u0027l16gwi5]","wordMean":"v.衰弱；变得消瘦"},{"word":"uncommitted","wordPron":"[`8nk4\u0027mitid]","wordMean":"adj.不受约束的,不承担责任的"},{"word":"measly","wordPron":"[\u0027mi:zli]","wordMean":"adj.患麻疹的,小得可怜的"},{"word":"dynamite","wordPron":"[\u0027dain4mait]","wordMean":"n.炸药;adj.动人心弦的"},{"word":"pilgrimage","wordPron":"[\u0027pilgrimid9]","wordMean":"n.朝圣之旅"},{"word":"bibliography","wordPron":"[`bibli\u00273gr4fi]","wordMean":"n.文献学；参考书目"},{"word":"perpetuity","wordPron":"[`p4:pi\u0027tjuiti]","wordMean":"n.永恒,永久"},{"word":"harpsichord","wordPron":"[\u0027h2:psik3:d]","wordMean":"n.键琴(钢琴前身)"},{"word":"quirk","wordPron":"[kw4:k]","wordMean":"n.奇事； 怪癖"},{"word":"armistice","wordPron":"[\u00272:mistis]","wordMean":"n.休战,停战"},{"word":"dynamo","wordPron":"[\u0027dain4m4u]","wordMean":"n.发电机"},{"word":"dummy","wordPron":"[\u0027d8mi]","wordMean":"n.人体模型,假人"},{"word":"generality","wordPron":"[`d9en4\u0027r1liti]","wordMean":"n.概述"},{"word":"sly","wordPron":"[slai]","wordMean":"adj.狡猾的,鬼鬼祟祟的"},{"word":"epithet","wordPron":"[\u0027epi7et]","wordMean":"n.(贬低人的)短语或形容词"},{"word":"pandemic","wordPron":"[p1n\u0027demik]","wordMean":"adj.(病)大范围流行的"},{"word":"remodel","wordPron":"[`ri:\u0027m3dl]","wordMean":"v.重建,改变形状"},{"word":"cumber","wordPron":"[\u0027k8mb4]","wordMean":"vt.拖累,妨碍"},{"word":"insecure","wordPron":"[insi\u0027kju4]","wordMean":"adj.不安全的,不稳定的;信心不足的"},{"word":"specimen","wordPron":"[\u0027spesim4n]","wordMean":"n.范例,样品,标本"},{"word":"infinitesimal","wordPron":"[`infini\u0027tesim(4)l]","wordMean":"adj.极微小的;n.极小的数"},{"word":"decorate","wordPron":"[\u0027dek4reit]","wordMean":"v.装饰某事物"},{"word":"gale","wordPron":"[geil]","wordMean":"n.狂风；一阵(笑声)"},{"word":"reactionary","wordPron":"[ri:\u00271k54n4ri]","wordMean":"adj.保守的,反动的"},{"word":"embitter","wordPron":"[im\u0027bit4]","wordMean":"v.使痛苦,使难受"},{"word":"boring","wordPron":"[\u0027b3:ri6]","wordMean":"adj.无趣的,乏味的"},{"word":"brat","wordPron":"[br1t]","wordMean":"n.孩子,顽童"},{"word":"tangy","wordPron":"[\u0027t16gi]","wordMean":"adj.强烈的,扑鼻的"}]